comfy_model_download/__init__.py
comfy_model_download/model_download.py
comfy_model_download-0.5.1.dist-info/LICENCE
comfy_model_download-0.5.1.dist-info/METADATA
comfy_model_download-0.5.1.dist-info/WHEEL
comfy_model_download-0.5.1.dist-info/top_level.txt
comfy_model_download-0.5.1.dist-info/RECORD
