Metadata-Version: 2.1
Name: comfy_model_download
Version: 0.5.1
Summary: A package to download AI models for ComfyUI from the internet or from private GCS buckets
Author-email: Sergio Tejón <stejon@freepik.com>
Project-URL: Homepage, https://github.com/freepik-company/comfy-model-download
Project-URL: Issues, https://https://github.com/freepik-company/comfy-model-download/issues
Classifier: Programming Language :: Python :: 3
Classifier: License :: OSI Approved :: MIT License
Classifier: Operating System :: OS Independent
Requires-Python: >=3.8
License-File: LICENCE
Requires-Dist: google-cloud-storage
Requires-Dist: requests
Requires-Dist: tqdm
Requires-Dist: urllib3
